[
    {
        "location_s": "california", 
        "fullName_s": "", 
        "lastName_s": "", 
        "email_s": "k3chu@ucsd.edu", 
        "postsPrivate_n": "0", 
        "username_s": "kevin5", 
        "profilePicUrl_s": "https://s3-us-west-1.amazonaws.com/sciqandroid-userfiles-mobilehub-631333021/user_images/12fe2bd2-50a9-4747-824e-62d4140f657f", 
        "firstName_s": "", 
        "gender_s": "Male", 
        "shortDescription_s": "the 5th kevin", 
        "photoId_s": "12fe2bd2-50a9-4747-824e-62d4140f657f", 
        "birthday_s": "03/17/1993", 
        "original_username_s": "kevin5", 
        "ethnicity_s": "Not Hispanic or Latino", 
        "userId_s": "us-west-2:023a2fa1-4f5d-4494-b63a-6b9eadd3f34e", 
        "race_s": "Asian", 
        "facebookId_s": ""
    }, 
    {
        "location_s": "abc", 
        "fullName_s": "", 
        "lastName_s": "", 
        "email_s": "", 
        "postsPrivate_n": "0", 
        "username_s": "abcuser", 
        "profilePicUrl_s": "https://s3-us-west-1.amazonaws.com/sciqandroid-userfiles-mobilehub-631333021/user_images/1870ddd8-610d-4690-9fb0-f0bf7fc223d3", 
        "firstName_s": "", 
        "gender_s": "", 
        "shortDescription_s": "test account", 
        "photoId_s": "1870ddd8-610d-4690-9fb0-f0bf7fc223d3", 
        "birthday_s": "08/24/2017", 
        "original_username_s": "", 
        "ethnicity_s": "", 
        "userId_s": "us-west-2:0794190d-9382-4d96-97b9-b0d9cee8e3b1", 
        "race_s": "", 
        "facebookId_s": ""
    }, 
    {
        "location_s": "corner of new and garvey", 
        "fullName_s": "", 
        "lastName_s": "", 
        "email_s": "", 
        "postsPrivate_n": "", 
        "username_s": "kevin7", 
        "profilePicUrl_s": "https://s3-us-west-1.amazonaws.com/sciqandroid-userfiles-mobilehub-631333021/user_images/", 
        "firstName_s": "", 
        "gender_s": "", 
        "shortDescription_s": "seven eleven baby", 
        "photoId_s": "", 
        "birthday_s": "11/04/1998", 
        "original_username_s": "", 
        "ethnicity_s": "", 
        "userId_s": "us-west-2:0881ad27-6806-442b-9e79-6c501d88715d", 
        "race_s": "", 
        "facebookId_s": ""
    }, 
    {
        "location_s": "san diego", 
        "fullName_s": "", 
        "lastName_s": "", 
        "email_s": "thefryingphan@gmail.com", 
        "postsPrivate_n": "0", 
        "username_s": "nickphan", 
        "profilePicUrl_s": "https://s3-us-west-1.amazonaws.com/sciqandroid-userfiles-mobilehub-631333021/user_images/65d9d5bf-68fa-4282-bd05-042f2491e82c", 
        "firstName_s": "", 
        "gender_s": "Male", 
        "shortDescription_s": "asdf", 
        "photoId_s": "65d9d5bf-68fa-4282-bd05-042f2491e82c", 
        "birthday_s": "10/18/2017", 
        "original_username_s": "nickphan", 
        "ethnicity_s": "Not Hispanic or Latino", 
        "userId_s": "us-west-2:09662b2e-5f04-476d-a7a5-6f00a501e1e9", 
        "race_s": "Asian", 
        "facebookId_s": ""
    }, 
    {
        "location_s": "Compton, California", 
        "fullName_s": "kevin chu", 
        "lastName_s": "Chu", 
        "email_s": "", 
        "postsPrivate_n": "0", 
        "username_s": "k3chu", 
        "profilePicUrl_s": "https://s3-us-west-1.amazonaws.com/sciqandroid-userfiles-mobilehub-631333021/user_images/k3chu", 
        "firstName_s": "Kevin", 
        "gender_s": "", 
        "shortDescription_s": "the kevs baby~", 
        "photoId_s": "", 
        "birthday_s": "10/14/2017", 
        "original_username_s": "", 
        "ethnicity_s": "", 
        "userId_s": "us-west-2:0a69c3ee-88f6-4127-a88d-9a26c5b67503", 
        "race_s": "", 
        "facebookId_s": ""
    }, 
    {
        "location_s": "abc", 
        "fullName_s": "", 
        "lastName_s": "", 
        "email_s": "", 
        "postsPrivate_n": "", 
        "username_s": "abc", 
        "profilePicUrl_s": "https://s3-us-west-1.amazonaws.com/sciqandroid-userfiles-mobilehub-631333021/user_images/abc", 
        "firstName_s": "", 
        "gender_s": "", 
        "shortDescription_s": "abc", 
        "photoId_s": "", 
        "birthday_s": "08/23/2017", 
        "original_username_s": "", 
        "ethnicity_s": "", 
        "userId_s": "us-west-2:0b71b97a-cf45-4481-8c8d-c716507db6ca", 
        "race_s": "", 
        "facebookId_s": ""
    }, 
    {
        "location_s": "aaa", 
        "fullName_s": "", 
        "lastName_s": "", 
        "email_s": "", 
        "postsPrivate_n": "0", 
        "username_s": "aug3117", 
        "profilePicUrl_s": "https://s3-us-west-1.amazonaws.com/sciqandroid-userfiles-mobilehub-631333021/user_images/5995e7b7-fdc1-4968-9b2f-3ee7212d557b", 
        "firstName_s": "", 
        "gender_s": "Male", 
        "shortDescription_s": "lorem ispum", 
        "photoId_s": "5995e7b7-fdc1-4968-9b2f-3ee7212d557b", 
        "birthday_s": "08/31/2017", 
        "original_username_s": "", 
        "ethnicity_s": "Hispanic or Latino", 
        "userId_s": "us-west-2:0d3444ff-85c1-4694-9b99-056332681cd5", 
        "race_s": "American Indian or Alaska Native", 
        "facebookId_s": ""
    }, 
    {
        "location_s": "test", 
        "fullName_s": "", 
        "lastName_s": "", 
        "email_s": "", 
        "postsPrivate_n": "", 
        "username_s": "aa", 
        "profilePicUrl_s": "https://s3-us-west-1.amazonaws.com/sciqandroid-userfiles-mobilehub-631333021/user_images/aa", 
        "firstName_s": "", 
        "gender_s": "", 
        "shortDescription_s": "test", 
        "photoId_s": "", 
        "birthday_s": "08/23/2017", 
        "original_username_s": "", 
        "ethnicity_s": "", 
        "userId_s": "us-west-2:106c0023-85a1-4365-ac98-896289686ee3", 
        "race_s": "", 
        "facebookId_s": ""
    }, 
    {
        "location_s": "test", 
        "fullName_s": "", 
        "lastName_s": "", 
        "email_s": "", 
        "postsPrivate_n": "", 
        "username_s": "testuser23", 
        "profilePicUrl_s": "https://s3-us-west-1.amazonaws.com/sciqandroid-userfiles-mobilehub-631333021/user_images/testuser23", 
        "firstName_s": "", 
        "gender_s": "", 
        "shortDescription_s": "test", 
        "photoId_s": "", 
        "birthday_s": "08/23/2017", 
        "original_username_s": "", 
        "ethnicity_s": "", 
        "userId_s": "us-west-2:10ed421d-85f3-4602-8eaa-2866b1e3f128", 
        "race_s": "", 
        "facebookId_s": ""
    }, 
    {
        "location_s": "gg", 
        "fullName_s": "", 
        "lastName_s": "", 
        "email_s": "jpgrgmgs@gmail.com", 
        "postsPrivate_n": "0", 
        "username_s": "gmgonzal3", 
        "profilePicUrl_s": "https://s3-us-west-1.amazonaws.com/sciqandroid-userfiles-mobilehub-631333021/user_images/a0a2c420-b292-491a-bdf7-f51e462fd88d", 
        "firstName_s": "", 
        "gender_s": "Male", 
        "shortDescription_s": "g", 
        "photoId_s": "a0a2c420-b292-491a-bdf7-f51e462fd88d", 
        "birthday_s": "09/18/2017", 
        "original_username_s": "gmgonzal3", 
        "ethnicity_s": "Hispanic or Latino", 
        "userId_s": "us-west-2:115cb04c-62b4-456b-872f-05470740e928", 
        "race_s": "American Indian or Alaska Native", 
        "facebookId_s": ""
    }, 
    {
        "location_s": "San Diego", 
        "fullName_s": "andrew lee", 
        "lastName_s": "lee", 
        "email_s": "naeuspam@gmail.com", 
        "postsPrivate_n": "0", 
        "username_s": "naeuspam", 
        "profilePicUrl_s": "https://s3-us-west-1.amazonaws.com/sciqandroid-userfiles-mobilehub-631333021/user_images/c69b669d-8c4d-403f-8a78-fafb8caedb32", 
        "firstName_s": "andrew", 
        "gender_s": "Male", 
        "shortDescription_s": "ASdas", 
        "photoId_s": "c69b669d-8c4d-403f-8a78-fafb8caedb32", 
        "birthday_s": "11/30/2017", 
        "original_username_s": "naeuspam", 
        "ethnicity_s": "Not Hispanic or Latino", 
        "userId_s": "us-west-2:153420c8-04bc-4c73-9ee5-592165af10e1", 
        "race_s": "Asian", 
        "facebookId_s": ""
    }, 
    {
        "location_s": "Hockenheim", 
        "fullName_s": "", 
        "lastName_s": "", 
        "email_s": "", 
        "postsPrivate_n": "0", 
        "username_s": "kevin20", 
        "profilePicUrl_s": "https://s3-us-west-1.amazonaws.com/sciqandroid-userfiles-mobilehub-631333021/user_images/a78b7b0b-9369-4e59-b81f-82941942c995", 
        "firstName_s": "", 
        "gender_s": "Male", 
        "shortDescription_s": "The sort of 20th kevin babbbbyyyy!!!!", 
        "photoId_s": "a78b7b0b-9369-4e59-b81f-82941942c995", 
        "birthday_s": "02/02/1992", 
        "original_username_s": "", 
        "ethnicity_s": "Hispanic or Latino", 
        "userId_s": "us-west-2:1af4271f-9aae-41ec-adec-04a0df2fb913", 
        "race_s": "Asian", 
        "facebookId_s": ""
    }, 
    {
        "location_s": "a", 
        "fullName_s": "", 
        "lastName_s": "", 
        "email_s": "swnam12+demo@gmail.com", 
        "postsPrivate_n": "0", 
        "username_s": "demo", 
        "profilePicUrl_s": "https://s3-us-west-1.amazonaws.com/sciqandroid-userfiles-mobilehub-631333021/user_images/a4436b90-adec-40a8-94f2-dbb2cf30f1f9", 
        "firstName_s": "", 
        "gender_s": "Male", 
        "shortDescription_s": "test", 
        "photoId_s": "a4436b90-adec-40a8-94f2-dbb2cf30f1f9", 
        "birthday_s": "09/11/2017", 
        "original_username_s": "demo", 
        "ethnicity_s": "Hispanic or Latino", 
        "userId_s": "us-west-2:1f006c01-9d14-4d58-a9aa-e77cd70d056e", 
        "race_s": "American Indian or Alaska Native", 
        "facebookId_s": ""
    }, 
    {
        "location_s": "92092", 
        "fullName_s": "", 
        "lastName_s": "", 
        "email_s": "", 
        "postsPrivate_n": "", 
        "username_s": "Sid", 
        "profilePicUrl_s": "https://s3-us-west-1.amazonaws.com/sciqandroid-userfiles-mobilehub-631333021/user_images/1f8609d4-a0aa-46dd-9d1c-3193471626d0", 
        "firstName_s": "", 
        "gender_s": "", 
        "shortDescription_s": "Hello, World!", 
        "photoId_s": "", 
        "birthday_s": "06/12/1997", 
        "original_username_s": "", 
        "ethnicity_s": "", 
        "userId_s": "us-west-2:1f8609d4-a0aa-46dd-9d1c-3193471626d0", 
        "race_s": "", 
        "facebookId_s": ""
    }, 
    {
        "location_s": "San Diego", 
        "fullName_s": "", 
        "lastName_s": "acevedo", 
        "email_s": "gilbert.acevedo.g@gmail.com", 
        "postsPrivate_n": "0", 
        "username_s": "GilAce", 
        "profilePicUrl_s": "https://s3-us-west-1.amazonaws.com/sciqandroid-userfiles-mobilehub-631333021/user_images/3c544a4d-255a-4508-ba21-f0c52f50ee95", 
        "firstName_s": "gilberto", 
        "gender_s": "Male", 
        "shortDescription_s": "I am GilAce!", 
        "photoId_s": "3c544a4d-255a-4508-ba21-f0c52f50ee95", 
        "birthday_s": "06/25/2018", 
        "original_username_s": "GilAce", 
        "ethnicity_s": "Hispanic or Latino", 
        "userId_s": "us-west-2:21dfe0fc-ac07-4634-8fa1-e949aa5a0579", 
        "race_s": "White", 
        "facebookId_s": ""
    }, 
    {
        "location_s": "aaa", 
        "fullName_s": "", 
        "lastName_s": "", 
        "email_s": "", 
        "postsPrivate_n": "", 
        "username_s": "aaa", 
        "profilePicUrl_s": "https://s3-us-west-1.amazonaws.com/sciqandroid-userfiles-mobilehub-631333021/user_images/aaa", 
        "firstName_s": "", 
        "gender_s": "", 
        "shortDescription_s": "aaa", 
        "photoId_s": "", 
        "birthday_s": "08/24/2017", 
        "original_username_s": "", 
        "ethnicity_s": "", 
        "userId_s": "us-west-2:230f950f-4da1-4466-a638-e7270f5e4f43", 
        "race_s": "", 
        "facebookId_s": ""
    }, 
    {
        "location_s": "San Diego", 
        "fullName_s": "", 
        "lastName_s": "acevedo", 
        "email_s": "giaceved@eng.ucsd.edu", 
        "postsPrivate_n": "0", 
        "username_s": "GilAce1", 
        "profilePicUrl_s": "https://s3-us-west-1.amazonaws.com/sciqandroid-userfiles-mobilehub-631333021/user_images/5d09b01e-c944-42ce-b079-6f88d10c6919", 
        "firstName_s": "gilberto", 
        "gender_s": "Male", 
        "shortDescription_s": "I am GilAce1", 
        "photoId_s": "5d09b01e-c944-42ce-b079-6f88d10c6919", 
        "birthday_s": "07/01/2018", 
        "original_username_s": "GilAce1", 
        "ethnicity_s": "Hispanic or Latino", 
        "userId_s": "us-west-2:23d542fc-31ef-47fd-9072-8dfe1e651eb1", 
        "race_s": "White", 
        "facebookId_s": ""
    }, 
    {
        "location_s": "San Diego", 
        "fullName_s": "", 
        "lastName_s": "", 
        "email_s": "", 
        "postsPrivate_n": "0", 
        "username_s": "BobbyIsAwesome", 
        "profilePicUrl_s": "https://s3-us-west-1.amazonaws.com/sciqandroid-userfiles-mobilehub-631333021/user_images/26da83bd-8a4a-4044-b06a-2d06d208e882", 
        "firstName_s": "", 
        "gender_s": "Male", 
        "shortDescription_s": "helllo", 
        "photoId_s": "26da83bd-8a4a-4044-b06a-2d06d208e882", 
        "birthday_s": "08/27/2017", 
        "original_username_s": "", 
        "ethnicity_s": "Not Hispanic or Latino", 
        "userId_s": "us-west-2:25f0f80d-afa4-4d14-89ef-de358ff47c1f", 
        "race_s": "Asian", 
        "facebookId_s": ""
    }, 
    {
        "location_s": "aaa", 
        "fullName_s": "", 
        "lastName_s": "", 
        "email_s": "swnam12+anam1@gmail.com", 
        "postsPrivate_n": "0", 
        "username_s": "anam12", 
        "profilePicUrl_s": "https://s3-us-west-1.amazonaws.com/sciqandroid-userfiles-mobilehub-631333021/user_images/2619a48c-e070-494a-81a2-f545ef3cec95", 
        "firstName_s": "", 
        "gender_s": "", 
        "shortDescription_s": "time for lunch! so hungry", 
        "photoId_s": "2619a48c-e070-494a-81a2-f545ef3cec95", 
        "birthday_s": "09/06/2017", 
        "original_username_s": "", 
        "ethnicity_s": "", 
        "userId_s": "us-west-2:276a049b-d5cb-4868-a24b-cd5d89100790", 
        "race_s": "", 
        "facebookId_s": ""
    }, 
    {
        "location_s": "hfhgfhfg", 
        "fullName_s": "", 
        "lastName_s": "", 
        "email_s": "", 
        "postsPrivate_n": "", 
        "username_s": "kevin10", 
        "profilePicUrl_s": "https://s3-us-west-1.amazonaws.com/sciqandroid-userfiles-mobilehub-631333021/user_images/kevin10", 
        "firstName_s": "", 
        "gender_s": "", 
        "shortDescription_s": "gfhfghfghgf", 
        "photoId_s": "", 
        "birthday_s": "08/13/2017", 
        "original_username_s": "", 
        "ethnicity_s": "", 
        "userId_s": "us-west-2:2a5fc270-d121-4355-9f34-1a1916469249", 
        "race_s": "", 
        "facebookId_s": ""
    }, 
    {
        "location_s": "Monte, Python", 
        "fullName_s": "", 
        "lastName_s": "", 
        "email_s": "", 
        "postsPrivate_n": "", 
        "username_s": "cfbn", 
        "profilePicUrl_s": "https://s3-us-west-1.amazonaws.com/sciqandroid-userfiles-mobilehub-631333021/user_images/ForTheGloryOfKen", 
        "firstName_s": "", 
        "gender_s": "", 
        "shortDescription_s": "Praise be unto Ken!", 
        "photoId_s": "", 
        "birthday_s": "6/22/93", 
        "original_username_s": "", 
        "ethnicity_s": "", 
        "userId_s": "us-west-2:2f13ca3c-1cd0-4ab7-ab18-bd0a1facb538", 
        "race_s": "", 
        "facebookId_s": ""
    }, 
    {
        "location_s": "a", 
        "fullName_s": "", 
        "lastName_s": "", 
        "email_s": "", 
        "postsPrivate_n": "0", 
        "username_s": "SeanSangwooNam", 
        "profilePicUrl_s": "https://s3-us-west-1.amazonaws.com/sciqandroid-userfiles-mobilehub-631333021/user_images/98912f2c-3906-4ad7-8d8f-439877723199", 
        "firstName_s": "", 
        "gender_s": "Male", 
        "shortDescription_s": "fb lo1", 
        "photoId_s": "98912f2c-3906-4ad7-8d8f-439877723199", 
        "birthday_s": "08/09/2015", 
        "original_username_s": "SeanSangwooNam", 
        "ethnicity_s": "Not Hispanic or Latino", 
        "userId_s": "us-west-2:324c1a23-1386-4bcb-9525-14d1267c5b89", 
        "race_s": "Asian", 
        "facebookId_s": "10155471915062836"
    }, 
    {
        "location_s": "a", 
        "fullName_s": "", 
        "lastName_s": "", 
        "email_s": "", 
        "postsPrivate_n": "1", 
        "username_s": "abcuser", 
        "profilePicUrl_s": "https://s3-us-west-1.amazonaws.com/sciqandroid-userfiles-mobilehub-631333021/user_images/e8279144-9dba-4706-b5cb-49888bd28f33", 
        "firstName_s": "", 
        "gender_s": "Male", 
        "shortDescription_s": "a", 
        "photoId_s": "e8279144-9dba-4706-b5cb-49888bd28f33", 
        "birthday_s": "08/27/2017", 
        "original_username_s": "", 
        "ethnicity_s": "", 
        "userId_s": "us-west-2:32f51e7a-846a-475d-9db3-5ea180e332a2", 
        "race_s": "", 
        "facebookId_s": ""
    }, 
    {
        "location_s": "loc", 
        "fullName_s": "", 
        "lastName_s": "", 
        "email_s": "swnam12+final@gmail.com", 
        "postsPrivate_n": "0", 
        "username_s": "final16", 
        "profilePicUrl_s": "https://s3-us-west-1.amazonaws.com/sciqandroid-userfiles-mobilehub-631333021/user_images/4d7ffb45-7c08-4f2a-a31d-ccdde1ab3a84", 
        "firstName_s": "", 
        "gender_s": "Male", 
        "shortDescription_s": "last one", 
        "photoId_s": "4d7ffb45-7c08-4f2a-a31d-ccdde1ab3a84", 
        "birthday_s": "09/08/2017", 
        "original_username_s": "final", 
        "ethnicity_s": "Hispanic or Latino", 
        "userId_s": "us-west-2:423f3439-1f9a-406a-bf1b-ce3adc32b3e0", 
        "race_s": "Asian", 
        "facebookId_s": ""
    }, 
    {
        "location_s": "trhjjb", 
        "fullName_s": "kevs pham", 
        "lastName_s": "pham", 
        "email_s": "kevin.chy007@yahoo.com", 
        "postsPrivate_n": "0", 
        "username_s": "kevin2826", 
        "profilePicUrl_s": "https://s3-us-west-1.amazonaws.com/sciqandroid-userfiles-mobilehub-631333021/user_images/629ba410-baf2-4024-8886-0cafc28be19f", 
        "firstName_s": "kevs", 
        "gender_s": "Male", 
        "shortDescription_s": "gdtygcvkjom ijfgj", 
        "photoId_s": "629ba410-baf2-4024-8886-0cafc28be19f", 
        "birthday_s": "05/23/2013", 
        "original_username_s": "kevin2826", 
        "ethnicity_s": "Not Hispanic or Latino", 
        "userId_s": "us-west-2:42b2b8a0-ebcf-4700-a064-287aac592704", 
        "race_s": "Black or African American", 
        "facebookId_s": ""
    }, 
    {
        "location_s": "La Jolla ", 
        "fullName_s": "", 
        "lastName_s": "bhavsar", 
        "email_s": "anandbhavsar01@gmail.com", 
        "postsPrivate_n": "0", 
        "username_s": "aX10mAt1c", 
        "profilePicUrl_s": "https://s3-us-west-1.amazonaws.com/sciqandroid-userfiles-mobilehub-631333021/user_images/03071a3c-1052-4a63-bea0-bc34b5b78c15", 
        "firstName_s": "anand", 
        "gender_s": "Male", 
        "shortDescription_s": "Not much else to say.", 
        "photoId_s": "03071a3c-1052-4a63-bea0-bc34b5b78c15", 
        "birthday_s": "10/23/1997", 
        "original_username_s": "aX10mAt1c", 
        "ethnicity_s": "Not Hispanic or Latino", 
        "userId_s": "us-west-2:47c7c28e-b917-4117-84de-a21726cae3f0", 
        "race_s": "Asian", 
        "facebookId_s": ""
    }, 
    {
        "location_s": "test", 
        "fullName_s": "", 
        "lastName_s": "", 
        "email_s": "", 
        "postsPrivate_n": "", 
        "username_s": "san012", 
        "profilePicUrl_s": "https://s3-us-west-1.amazonaws.com/sciqandroid-userfiles-mobilehub-631333021/user_images/san012", 
        "firstName_s": "", 
        "gender_s": "", 
        "shortDescription_s": "test", 
        "photoId_s": "", 
        "birthday_s": "07/15/1992", 
        "original_username_s": "", 
        "ethnicity_s": "", 
        "userId_s": "us-west-2:491b2d91-7a61-4eb6-9ce2-2821444d7a70", 
        "race_s": "", 
        "facebookId_s": ""
    }, 
    {
        "location_s": "a", 
        "fullName_s": "", 
        "lastName_s": "", 
        "email_s": "", 
        "postsPrivate_n": "", 
        "username_s": "aug24", 
        "profilePicUrl_s": "https://s3-us-west-1.amazonaws.com/sciqandroid-userfiles-mobilehub-631333021/user_images/aug24", 
        "firstName_s": "", 
        "gender_s": "", 
        "shortDescription_s": "test", 
        "photoId_s": "", 
        "birthday_s": "08/24/2017", 
        "original_username_s": "", 
        "ethnicity_s": "", 
        "userId_s": "us-west-2:4b9b9c44-b146-4b47-8eab-65fc7d3c00b1", 
        "race_s": "", 
        "facebookId_s": ""
    }, 
    {
        "location_s": "asd", 
        "fullName_s": "", 
        "lastName_s": "", 
        "email_s": "", 
        "postsPrivate_n": "", 
        "username_s": "hi", 
        "profilePicUrl_s": "https://s3-us-west-1.amazonaws.com/sciqandroid-userfiles-mobilehub-631333021/user_images/", 
        "firstName_s": "", 
        "gender_s": "", 
        "shortDescription_s": "test", 
        "photoId_s": "", 
        "birthday_s": "08/17/2017", 
        "original_username_s": "", 
        "ethnicity_s": "", 
        "userId_s": "us-west-2:4d121f9a-b1ab-43dc-a02c-e8979b178096", 
        "race_s": "", 
        "facebookId_s": ""
    }, 
    {
        "location_s": "las vegas", 
        "fullName_s": "", 
        "lastName_s": "", 
        "email_s": "", 
        "postsPrivate_n": "0", 
        "username_s": "a11", 
        "profilePicUrl_s": "https://s3-us-west-1.amazonaws.com/sciqandroid-userfiles-mobilehub-631333021/user_images/f03a4a88-57ed-4eca-b4e6-daff7bf54892", 
        "firstName_s": "", 
        "gender_s": "Male", 
        "shortDescription_s": "a user 11", 
        "photoId_s": "f03a4a88-57ed-4eca-b4e6-daff7bf54892", 
        "birthday_s": "01/29/2011", 
        "original_username_s": "", 
        "ethnicity_s": "Hispanic or Latino", 
        "userId_s": "us-west-2:4f2cd71a-0b23-415b-9831-faf3fb0c8165", 
        "race_s": "American Indian or Alaska Native", 
        "facebookId_s": ""
    }, 
    {
        "location_s": "San Diego", 
        "fullName_s": "", 
        "lastName_s": "temple-wong", 
        "email_s": "michele.templewong@gmail.com", 
        "postsPrivate_n": "0", 
        "username_s": "mtsciq", 
        "profilePicUrl_s": "https://s3-us-west-1.amazonaws.com/sciqandroid-userfiles-mobilehub-631333021/user_images/d4919d7a-2fd9-48e3-a478-a902ad988905", 
        "firstName_s": "michele", 
        "gender_s": "Male", 
        "shortDescription_s": "ktchgkhk", 
        "photoId_s": "d4919d7a-2fd9-48e3-a478-a902ad988905", 
        "birthday_s": "07/04/2018", 
        "original_username_s": "mtsciq", 
        "ethnicity_s": "Hispanic or Latino", 
        "userId_s": "us-west-2:5259b3d8-60dd-4e3f-8b2e-614bd51fca9d", 
        "race_s": "Asian", 
        "facebookId_s": ""
    }, 
    {
        "location_s": "testing", 
        "fullName_s": "", 
        "lastName_s": "", 
        "email_s": "", 
        "postsPrivate_n": "", 
        "username_s": "testuser", 
        "profilePicUrl_s": "https://s3-us-west-1.amazonaws.com/sciqandroid-userfiles-mobilehub-631333021/user_images/", 
        "firstName_s": "", 
        "gender_s": "", 
        "shortDescription_s": "test user reporting for duty", 
        "photoId_s": "", 
        "birthday_s": "08/16/1994", 
        "original_username_s": "", 
        "ethnicity_s": "", 
        "userId_s": "us-west-2:630a71f3-52a5-438e-adaf-f4fcdd2b7a51", 
        "race_s": "", 
        "facebookId_s": ""
    }, 
    {
        "location_s": "Los Altos", 
        "fullName_s": "", 
        "lastName_s": "b", 
        "email_s": "anandtest0@gmail.com", 
        "postsPrivate_n": "0", 
        "username_s": "Test1976245", 
        "profilePicUrl_s": "https://s3-us-west-1.amazonaws.com/sciqandroid-userfiles-mobilehub-631333021/user_images/22784587-5a45-4fd7-9af3-da94eef1b092", 
        "firstName_s": "a", 
        "gender_s": "Male", 
        "shortDescription_s": "ssrgarfgs", 
        "photoId_s": "22784587-5a45-4fd7-9af3-da94eef1b092", 
        "birthday_s": "03/24/2018", 
        "original_username_s": "Test1976245", 
        "ethnicity_s": "Not Hispanic or Latino", 
        "userId_s": "us-west-2:6564487c-e86c-4131-9469-5716b7d8a47d", 
        "race_s": "Asian", 
        "facebookId_s": ""
    }, 
    {
        "location_s": "a", 
        "fullName_s": "", 
        "lastName_s": "", 
        "email_s": "swnam12+a6@gmail.com", 
        "postsPrivate_n": "0", 
        "username_s": "a600", 
        "profilePicUrl_s": "https://s3-us-west-1.amazonaws.com/sciqandroid-userfiles-mobilehub-631333021/user_images/bfb0bc09-24a3-4a28-93be-34be762796fc", 
        "firstName_s": "", 
        "gender_s": "", 
        "shortDescription_s": "last test almost 230", 
        "photoId_s": "bfb0bc09-24a3-4a28-93be-34be762796fc", 
        "birthday_s": "09/04/2017", 
        "original_username_s": "", 
        "ethnicity_s": "", 
        "userId_s": "us-west-2:66b0d238-b2c4-47b0-8180-1dd6ab5bebec", 
        "race_s": "", 
        "facebookId_s": ""
    }, 
    {
        "location_s": "test aa a ", 
        "fullName_s": "", 
        "lastName_s": "", 
        "email_s": "", 
        "postsPrivate_n": "", 
        "username_s": "swnam121", 
        "profilePicUrl_s": "https://s3-us-west-1.amazonaws.com/sciqandroid-userfiles-mobilehub-631333021/user_images/swnam121", 
        "firstName_s": "", 
        "gender_s": "", 
        "shortDescription_s": "test testest test ", 
        "photoId_s": "", 
        "birthday_s": "08/17/2017", 
        "original_username_s": "", 
        "ethnicity_s": "", 
        "userId_s": "us-west-2:6d0f9e98-4696-4928-aa23-4d58fcecb87d", 
        "race_s": "", 
        "facebookId_s": ""
    }, 
    {
        "location_s": "test", 
        "fullName_s": "", 
        "lastName_s": "", 
        "email_s": "", 
        "postsPrivate_n": "", 
        "username_s": "aa", 
        "profilePicUrl_s": "https://s3-us-west-1.amazonaws.com/sciqandroid-userfiles-mobilehub-631333021/user_images/aa", 
        "firstName_s": "", 
        "gender_s": "", 
        "shortDescription_s": "test", 
        "photoId_s": "", 
        "birthday_s": "08/23/2017", 
        "original_username_s": "", 
        "ethnicity_s": "", 
        "userId_s": "us-west-2:6ebae440-f8fc-4d6a-9981-1158e63e6c34", 
        "race_s": "", 
        "facebookId_s": ""
    }, 
    {
        "location_s": "abc22", 
        "fullName_s": "", 
        "lastName_s": "", 
        "email_s": "", 
        "postsPrivate_n": "", 
        "username_s": "testuser22", 
        "profilePicUrl_s": "https://s3-us-west-1.amazonaws.com/sciqandroid-userfiles-mobilehub-631333021/user_images/testuser22", 
        "firstName_s": "", 
        "gender_s": "", 
        "shortDescription_s": "testing22", 
        "photoId_s": "", 
        "birthday_s": "08/22/2012", 
        "original_username_s": "", 
        "ethnicity_s": "", 
        "userId_s": "us-west-2:722c9cfb-e14c-4f10-9fd6-48ab1eb0d9a6", 
        "race_s": "", 
        "facebookId_s": ""
    }, 
    {
        "location_s": "aaa", 
        "fullName_s": "", 
        "lastName_s": "", 
        "email_s": "", 
        "postsPrivate_n": "0", 
        "username_s": "aswnam", 
        "profilePicUrl_s": "https://s3-us-west-1.amazonaws.com/sciqandroid-userfiles-mobilehub-631333021/user_images/7fee6523-630f-409a-90d2-fe3119461d38", 
        "firstName_s": "", 
        "gender_s": "", 
        "shortDescription_s": "another test user", 
        "photoId_s": "7fee6523-630f-409a-90d2-fe3119461d38", 
        "birthday_s": "09/06/2016", 
        "original_username_s": "", 
        "ethnicity_s": "", 
        "userId_s": "us-west-2:74484f62-c47f-483d-8848-d092299a077d", 
        "race_s": "", 
        "facebookId_s": ""
    }, 
    {
        "location_s": "San Diego", 
        "fullName_s": "", 
        "lastName_s": "", 
        "email_s": "", 
        "postsPrivate_n": "", 
        "username_s": "jackcho", 
        "profilePicUrl_s": "https://s3-us-west-1.amazonaws.com/sciqandroid-userfiles-mobilehub-631333021/user_images/jackcho", 
        "firstName_s": "", 
        "gender_s": "", 
        "shortDescription_s": "Person with eczema and acne", 
        "photoId_s": "", 
        "birthday_s": "11/09/1995", 
        "original_username_s": "", 
        "ethnicity_s": "", 
        "userId_s": "us-west-2:754fc624-a84e-4201-ad4b-6e73bd72d2df", 
        "race_s": "", 
        "facebookId_s": ""
    }, 
    {
        "location_s": "a", 
        "fullName_s": "", 
        "lastName_s": "", 
        "email_s": "", 
        "postsPrivate_n": "0", 
        "username_s": "asep5", 
        "profilePicUrl_s": "https://s3-us-west-1.amazonaws.com/sciqandroid-userfiles-mobilehub-631333021/user_images/d391a15b-38b6-439f-b90f-707621372d11", 
        "firstName_s": "", 
        "gender_s": "Male", 
        "shortDescription_s": "testing in september", 
        "photoId_s": "d391a15b-38b6-439f-b90f-707621372d11", 
        "birthday_s": "09/05/2017", 
        "original_username_s": "", 
        "ethnicity_s": "Not Hispanic or Latino", 
        "userId_s": "us-west-2:82d328d7-8b0c-4a63-b746-2b50af13e558", 
        "race_s": "Black or African American", 
        "facebookId_s": ""
    }, 
    {
        "location_s": "auser", 
        "fullName_s": "", 
        "lastName_s": "", 
        "email_s": "", 
        "postsPrivate_n": "0", 
        "username_s": "auser", 
        "profilePicUrl_s": "https://s3-us-west-1.amazonaws.com/sciqandroid-userfiles-mobilehub-631333021/user_images/2b1e378a-469a-4606-af02-a10a66cf5931", 
        "firstName_s": "", 
        "gender_s": "Male", 
        "shortDescription_s": "auser", 
        "photoId_s": "2b1e378a-469a-4606-af02-a10a66cf5931", 
        "birthday_s": "09/05/2017", 
        "original_username_s": "", 
        "ethnicity_s": "Hispanic or Latino", 
        "userId_s": "us-west-2:8c4f4db7-28d7-43ee-989a-ee64e5b16be4", 
        "race_s": "Asian", 
        "facebookId_s": ""
    }, 
    {
        "location_s": "La Jolla ", 
        "fullName_s": "", 
        "lastName_s": "bhavsar", 
        "email_s": "abhavsar@ucsd.edu", 
        "postsPrivate_n": "0", 
        "username_s": "TestA", 
        "profilePicUrl_s": "https://s3-us-west-1.amazonaws.com/sciqandroid-userfiles-mobilehub-631333021/user_images/fb1f632b-3a3b-4d22-a12d-c9e416bc2a28", 
        "firstName_s": "anand", 
        "gender_s": "Male", 
        "shortDescription_s": "Not much else to say.", 
        "photoId_s": "fb1f632b-3a3b-4d22-a12d-c9e416bc2a28", 
        "birthday_s": "10/23/1997", 
        "original_username_s": "TestA", 
        "ethnicity_s": "Not Hispanic or Latino", 
        "userId_s": "us-west-2:8cad5523-1a9c-4059-9abd-b0b2fc674622", 
        "race_s": "Asian", 
        "facebookId_s": ""
    }, 
    {
        "location_s": "hi", 
        "fullName_s": "", 
        "lastName_s": "", 
        "email_s": "", 
        "postsPrivate_n": "0", 
        "username_s": "hi", 
        "profilePicUrl_s": "https://s3-us-west-1.amazonaws.com/sciqandroid-userfiles-mobilehub-631333021/user_images/d58ccedb-70d1-49ab-a81d-b8a372d86831", 
        "firstName_s": "", 
        "gender_s": "Female", 
        "shortDescription_s": "hi", 
        "photoId_s": "d58ccedb-70d1-49ab-a81d-b8a372d86831", 
        "birthday_s": "08/28/2017", 
        "original_username_s": "", 
        "ethnicity_s": "Hispanic or Latino", 
        "userId_s": "us-west-2:8d1b8c39-a9c0-4aeb-965d-be48d01cfae2", 
        "race_s": "Black or African American", 
        "facebookId_s": ""
    }, 
    {
        "location_s": "a", 
        "fullName_s": "", 
        "lastName_s": "", 
        "email_s": "", 
        "postsPrivate_n": "0", 
        "username_s": "a3", 
        "profilePicUrl_s": "https://s3-us-west-1.amazonaws.com/sciqandroid-userfiles-mobilehub-631333021/user_images/45e962d4-3776-4567-95d5-c33696edd60e", 
        "firstName_s": "", 
        "gender_s": "Male", 
        "shortDescription_s": "aa", 
        "photoId_s": "45e962d4-3776-4567-95d5-c33696edd60e", 
        "birthday_s": "09/05/2017", 
        "original_username_s": "", 
        "ethnicity_s": "Hispanic or Latino", 
        "userId_s": "us-west-2:8d91e9e4-f2c7-4bca-bef6-2ea494918a37", 
        "race_s": "American Indian or Alaska Native", 
        "facebookId_s": ""
    }, 
    {
        "location_s": "aasdfabb", 
        "fullName_s": "", 
        "lastName_s": "", 
        "email_s": "swnam12+a1a@gmail.com", 
        "postsPrivate_n": "0", 
        "username_s": "a1a", 
        "profilePicUrl_s": "https://s3-us-west-1.amazonaws.com/sciqandroid-userfiles-mobilehub-631333021/user_images/0967f852-16f9-4624-b60d-6eb7c85de507", 
        "firstName_s": "", 
        "gender_s": "Female", 
        "shortDescription_s": "current time is 1323 hours", 
        "photoId_s": "0967f852-16f9-4624-b60d-6eb7c85de507", 
        "birthday_s": "09/06/2017", 
        "original_username_s": "", 
        "ethnicity_s": "Not Hispanic or Latino", 
        "userId_s": "us-west-2:8e9aa1f2-f98f-440c-945f-372febe9b48a", 
        "race_s": "Asian", 
        "facebookId_s": ""
    }, 
    {
        "location_s": "a", 
        "fullName_s": "", 
        "lastName_s": "", 
        "email_s": "", 
        "postsPrivate_n": "0", 
        "username_s": "a", 
        "profilePicUrl_s": "https://s3-us-west-1.amazonaws.com/sciqandroid-userfiles-mobilehub-631333021/user_images/4954aa3d-28cf-414a-b0fb-b686f1541019", 
        "firstName_s": "", 
        "gender_s": "", 
        "shortDescription_s": "a", 
        "photoId_s": "4954aa3d-28cf-414a-b0fb-b686f1541019", 
        "birthday_s": "08/27/2017", 
        "original_username_s": "", 
        "ethnicity_s": "", 
        "userId_s": "us-west-2:90406320-05ea-46a3-9040-20e23f7bea45", 
        "race_s": "", 
        "facebookId_s": ""
    }, 
    {
        "location_s": "hi", 
        "fullName_s": "", 
        "lastName_s": "", 
        "email_s": "", 
        "postsPrivate_n": "0", 
        "username_s": "phil", 
        "profilePicUrl_s": "https://s3-us-west-1.amazonaws.com/sciqandroid-userfiles-mobilehub-631333021/user_images/beebdfec-00cb-4ba6-afd3-84aa77adc0b2", 
        "firstName_s": "", 
        "gender_s": "Male", 
        "shortDescription_s": "hi", 
        "photoId_s": "beebdfec-00cb-4ba6-afd3-84aa77adc0b2", 
        "birthday_s": "08/28/2017", 
        "original_username_s": "", 
        "ethnicity_s": "Hispanic or Latino", 
        "userId_s": "us-west-2:95665e30-1925-4710-9aad-d8354ff970df", 
        "race_s": "White", 
        "facebookId_s": ""
    }, 
    {
        "location_s": "America", 
        "fullName_s": "fabian choi", 
        "lastName_s": "choi", 
        "email_s": "cfbn95j@gmail.com", 
        "postsPrivate_n": "0", 
        "username_s": "c.fbn95", 
        "profilePicUrl_s": "https://s3-us-west-1.amazonaws.com/sciqandroid-userfiles-mobilehub-631333021/user_images/03bc8e74-88a9-4aa6-92f8-a5b0ffd6dd95", 
        "firstName_s": "fabian", 
        "gender_s": "Male", 
        "shortDescription_s": "Testing all stuff", 
        "photoId_s": "03bc8e74-88a9-4aa6-92f8-a5b0ffd6dd95", 
        "birthday_s": "10/26/2017", 
        "original_username_s": "c.fbn95", 
        "ethnicity_s": "Not Hispanic or Latino", 
        "userId_s": "us-west-2:971ffd4a-f267-4712-a423-17fb306bd2ed", 
        "race_s": "Asian", 
        "facebookId_s": ""
    }, 
    {
        "location_s": "san diego", 
        "fullName_s": "", 
        "lastName_s": "xie", 
        "email_s": "zephre0101@gmail.com", 
        "postsPrivate_n": "0", 
        "username_s": "chris01", 
        "profilePicUrl_s": "https://s3-us-west-1.amazonaws.com/sciqandroid-userfiles-mobilehub-631333021/user_images/ed3f7ab9-ebfa-49ef-8dc9-97f3db354508", 
        "firstName_s": "chris", 
        "gender_s": "Male", 
        "shortDescription_s": "Anonymous Software Engineer", 
        "photoId_s": "ed3f7ab9-ebfa-49ef-8dc9-97f3db354508", 
        "birthday_s": "06/27/2018", 
        "original_username_s": "chris01", 
        "ethnicity_s": "Not Hispanic or Latino", 
        "userId_s": "us-west-2:9e605c15-0a37-4741-99ea-b71ce6c34aa7", 
        "race_s": "Asian", 
        "facebookId_s": ""
    }, 
    {
        "location_s": "La Jolla", 
        "fullName_s": "", 
        "lastName_s": "", 
        "email_s": "imsidthesquid@gmail.com", 
        "postsPrivate_n": "0", 
        "username_s": "bobby", 
        "profilePicUrl_s": "https://s3-us-west-1.amazonaws.com/sciqandroid-userfiles-mobilehub-631333021/user_images/5479f65e-e9df-47ac-847e-a3c6bf0395c8", 
        "firstName_s": "", 
        "gender_s": "Male", 
        "shortDescription_s": "I am bobby", 
        "photoId_s": "5479f65e-e9df-47ac-847e-a3c6bf0395c8", 
        "birthday_s": "09/15/2017", 
        "original_username_s": "bobby", 
        "ethnicity_s": "Not Hispanic or Latino", 
        "userId_s": "us-west-2:a455ad45-b749-4254-84c9-bc6bfe7fd1bc", 
        "race_s": "Asian", 
        "facebookId_s": ""
    }, 
    {
        "location_s": "Monte, Python", 
        "fullName_s": "", 
        "lastName_s": "", 
        "email_s": "", 
        "postsPrivate_n": "", 
        "username_s": "jackW", 
        "profilePicUrl_s": "https://s3-us-west-1.amazonaws.com/sciqandroid-userfiles-mobilehub-631333021/user_images/jackW", 
        "firstName_s": "", 
        "gender_s": "", 
        "shortDescription_s": "Praise be unto Ken!", 
        "photoId_s": "", 
        "birthday_s": "6/22/93", 
        "original_username_s": "", 
        "ethnicity_s": "", 
        "userId_s": "us-west-2:ac841cfa-d67e-4549-a338-7bc585ee9c39", 
        "race_s": "", 
        "facebookId_s": ""
    }, 
    {
        "location_s": "abc", 
        "fullName_s": "", 
        "lastName_s": "", 
        "email_s": "", 
        "postsPrivate_n": "0", 
        "username_s": "abcuser", 
        "profilePicUrl_s": "https://s3-us-west-1.amazonaws.com/sciqandroid-userfiles-mobilehub-631333021/user_images/1870ddd8-610d-4690-9fb0-f0bf7fc223d3", 
        "firstName_s": "", 
        "gender_s": "", 
        "shortDescription_s": "i am the alphabet", 
        "photoId_s": "1870ddd8-610d-4690-9fb0-f0bf7fc223d3", 
        "birthday_s": "08/24/2017", 
        "original_username_s": "", 
        "ethnicity_s": "", 
        "userId_s": "us-west-2:ae091930-39f0-44d4-8431-ec7d4afb333b", 
        "race_s": "", 
        "facebookId_s": ""
    }, 
    {
        "location_s": "Sealand", 
        "fullName_s": "", 
        "lastName_s": "", 
        "email_s": "", 
        "postsPrivate_n": "0", 
        "username_s": "kevin15", 
        "profilePicUrl_s": "https://s3-us-west-1.amazonaws.com/sciqandroid-userfiles-mobilehub-631333021/user_images/7039f238-c376-4bb4-a7f9-ee1514843ada", 
        "firstName_s": "", 
        "gender_s": "", 
        "shortDescription_s": "no longer the 5th", 
        "photoId_s": "7039f238-c376-4bb4-a7f9-ee1514843ada", 
        "birthday_s": "08/29/2011", 
        "original_username_s": "", 
        "ethnicity_s": "", 
        "userId_s": "us-west-2:af556dfa-2c22-4669-93e6-df16bab762ce", 
        "race_s": "", 
        "facebookId_s": ""
    }, 
    {
        "location_s": "last day of summer", 
        "fullName_s": "", 
        "lastName_s": "", 
        "email_s": "", 
        "postsPrivate_n": "0", 
        "username_s": "aug31", 
        "profilePicUrl_s": "https://s3-us-west-1.amazonaws.com/sciqandroid-userfiles-mobilehub-631333021/user_images/bd58ed59-b84f-4d52-adba-08efe86060d8", 
        "firstName_s": "", 
        "gender_s": "", 
        "shortDescription_s": "last day of august", 
        "photoId_s": "bd58ed59-b84f-4d52-adba-08efe86060d8", 
        "birthday_s": "08/31/2017", 
        "original_username_s": "", 
        "ethnicity_s": "", 
        "userId_s": "us-west-2:af7031ba-fb3c-4d6b-b259-7fc624870abf", 
        "race_s": "", 
        "facebookId_s": ""
    }, 
    {
        "location_s": "San Diego, CA", 
        "fullName_s": "", 
        "lastName_s": "", 
        "email_s": "michele.templewong@gmail.com", 
        "postsPrivate_n": "0", 
        "username_s": "mtemple", 
        "profilePicUrl_s": "https://s3-us-west-1.amazonaws.com/sciqandroid-userfiles-mobilehub-631333021/user_images/b40f7d63-b70a-4b69-8363-0ab66696676e", 
        "firstName_s": "", 
        "gender_s": "Female", 
        "shortDescription_s": "Looking to feel comfortable in my skin", 
        "photoId_s": "b40f7d63-b70a-4b69-8363-0ab66696676e", 
        "birthday_s": "09/19/1986", 
        "original_username_s": "mtemple", 
        "ethnicity_s": "Not Hispanic or Latino", 
        "userId_s": "us-west-2:b07fc8ba-717d-4d44-bfae-febee7213232", 
        "race_s": "White", 
        "facebookId_s": ""
    }, 
    {
        "location_s": "fdsfsdf", 
        "fullName_s": "", 
        "lastName_s": "", 
        "email_s": "", 
        "postsPrivate_n": "0", 
        "username_s": "hongda", 
        "profilePicUrl_s": "https://s3-us-west-1.amazonaws.com/sciqandroid-userfiles-mobilehub-631333021/user_images/2e3aa299-920b-4bed-bbcd-5b87552a3de9", 
        "firstName_s": "", 
        "gender_s": "", 
        "shortDescription_s": "fdsfdsfdsf", 
        "photoId_s": "2e3aa299-920b-4bed-bbcd-5b87552a3de9", 
        "birthday_s": "08/25/2009", 
        "original_username_s": "", 
        "ethnicity_s": "", 
        "userId_s": "us-west-2:b33db873-feef-4980-8fdf-af88ddfaa9e2", 
        "race_s": "", 
        "facebookId_s": ""
    }, 
    {
        "location_s": "ngfngfn", 
        "fullName_s": "", 
        "lastName_s": "", 
        "email_s": "", 
        "postsPrivate_n": "", 
        "username_s": "kevin11", 
        "profilePicUrl_s": "https://s3-us-west-1.amazonaws.com/sciqandroid-userfiles-mobilehub-631333021/user_images/kevin11", 
        "firstName_s": "", 
        "gender_s": "", 
        "shortDescription_s": "nbgnbgfn", 
        "photoId_s": "", 
        "birthday_s": "08/13/2017", 
        "original_username_s": "", 
        "ethnicity_s": "", 
        "userId_s": "us-west-2:b949f47c-c667-4498-8c4f-0a72dc0f8558", 
        "race_s": "", 
        "facebookId_s": ""
    }, 
    {
        "location_s": "abc", 
        "fullName_s": "", 
        "lastName_s": "", 
        "email_s": "", 
        "postsPrivate_n": "0", 
        "username_s": "abcuser", 
        "profilePicUrl_s": "https://s3-us-west-1.amazonaws.com/sciqandroid-userfiles-mobilehub-631333021/user_images/1870ddd8-610d-4690-9fb0-f0bf7fc223d3", 
        "firstName_s": "", 
        "gender_s": "", 
        "shortDescription_s": "lorem ispum", 
        "photoId_s": "1870ddd8-610d-4690-9fb0-f0bf7fc223d3", 
        "birthday_s": "08/24/2017", 
        "original_username_s": "", 
        "ethnicity_s": "", 
        "userId_s": "us-west-2:bbac5192-13f3-4a6c-b967-4613a56a987e", 
        "race_s": "", 
        "facebookId_s": ""
    }, 
    {
        "location_s": "141", 
        "fullName_s": "", 
        "lastName_s": "", 
        "email_s": "", 
        "postsPrivate_n": "0", 
        "username_s": "abcuser1", 
        "profilePicUrl_s": "https://s3-us-west-1.amazonaws.com/sciqandroid-userfiles-mobilehub-631333021/user_images/fb161ed5-1c51-407a-a60f-28ceec416d9c", 
        "firstName_s": "", 
        "gender_s": "Female", 
        "shortDescription_s": "xyz", 
        "photoId_s": "fb161ed5-1c51-407a-a60f-28ceec416d9c", 
        "birthday_s": "08/22/2017", 
        "original_username_s": "", 
        "ethnicity_s": "Not Hispanic or Latino", 
        "userId_s": "us-west-2:c154a608-fbf4-4d6e-823c-ea54e843959e", 
        "race_s": "American Indian or Alaska Native", 
        "facebookId_s": ""
    }, 
    {
        "location_s": "ab", 
        "fullName_s": "", 
        "lastName_s": "", 
        "email_s": "", 
        "postsPrivate_n": "0", 
        "username_s": "testuser12345", 
        "profilePicUrl_s": "https://s3-us-west-1.amazonaws.com/sciqandroid-userfiles-mobilehub-631333021/user_images/1f4868a0-eee8-4494-84a7-f7ed130289d8", 
        "firstName_s": "", 
        "gender_s": "", 
        "shortDescription_s": "description here 222asdfas", 
        "photoId_s": "1f4868a0-eee8-4494-84a7-f7ed130289d8", 
        "birthday_s": "09/06/2017", 
        "original_username_s": "", 
        "ethnicity_s": "", 
        "userId_s": "us-west-2:c1bb1d14-7d6c-42c5-b81f-9e1ea82ccbcd", 
        "race_s": "", 
        "facebookId_s": ""
    }, 
    {
        "location_s": "summer", 
        "fullName_s": "", 
        "lastName_s": "", 
        "email_s": "", 
        "postsPrivate_n": "0", 
        "username_s": "aug27", 
        "profilePicUrl_s": "https://s3-us-west-1.amazonaws.com/sciqandroid-userfiles-mobilehub-631333021/user_images/5e4e3c81-289b-46bb-a830-313106eee42c", 
        "firstName_s": "", 
        "gender_s": "", 
        "shortDescription_s": "august twenty seven", 
        "photoId_s": "5e4e3c81-289b-46bb-a830-313106eee42c", 
        "birthday_s": "08/27/2017", 
        "original_username_s": "", 
        "ethnicity_s": "", 
        "userId_s": "us-west-2:c1fc8f3c-973a-4ef1-beff-9c42bdf5004a", 
        "race_s": "", 
        "facebookId_s": ""
    }, 
    {
        "location_s": "a", 
        "fullName_s": "", 
        "lastName_s": "", 
        "email_s": "", 
        "postsPrivate_n": "", 
        "username_s": "aug22", 
        "profilePicUrl_s": "https://s3-us-west-1.amazonaws.com/sciqandroid-userfiles-mobilehub-631333021/user_images/aug22", 
        "firstName_s": "", 
        "gender_s": "", 
        "shortDescription_s": "a", 
        "photoId_s": "", 
        "birthday_s": "02/15/2009", 
        "original_username_s": "", 
        "ethnicity_s": "", 
        "userId_s": "us-west-2:c9b1d4aa-91f1-4924-963e-9d53fa503c56", 
        "race_s": "", 
        "facebookId_s": ""
    }, 
    {
        "location_s": "a", 
        "fullName_s": "", 
        "lastName_s": "", 
        "email_s": "", 
        "postsPrivate_n": "0", 
        "username_s": "a123", 
        "profilePicUrl_s": "https://s3-us-west-1.amazonaws.com/sciqandroid-userfiles-mobilehub-631333021/user_images/51139a03-b9cd-44f7-914a-7707db67a868", 
        "firstName_s": "", 
        "gender_s": "Male", 
        "shortDescription_s": "lorem ispum", 
        "photoId_s": "51139a03-b9cd-44f7-914a-7707db67a868", 
        "birthday_s": "08/27/2017", 
        "original_username_s": "", 
        "ethnicity_s": "Hispanic or Latino", 
        "userId_s": "us-west-2:c9c370cf-20f0-4936-a87b-16c198fda426", 
        "race_s": "Asian", 
        "facebookId_s": ""
    }, 
    {
        "location_s": "a", 
        "fullName_s": "", 
        "lastName_s": "", 
        "email_s": "", 
        "postsPrivate_n": "", 
        "username_s": "swnam121", 
        "profilePicUrl_s": "https://s3-us-west-1.amazonaws.com/sciqandroid-userfiles-mobilehub-631333021/user_images/swnam121", 
        "firstName_s": "", 
        "gender_s": "", 
        "shortDescription_s": "test", 
        "photoId_s": "", 
        "birthday_s": "08/19/2017", 
        "original_username_s": "", 
        "ethnicity_s": "", 
        "userId_s": "us-west-2:ca76ec37-dd98-48ba-babf-8f53952cf70b", 
        "race_s": "", 
        "facebookId_s": ""
    }, 
    {
        "location_s": "abcdefghj", 
        "fullName_s": "", 
        "lastName_s": "", 
        "email_s": "", 
        "postsPrivate_n": "0", 
        "username_s": "abcuser1", 
        "profilePicUrl_s": "https://s3-us-west-1.amazonaws.com/sciqandroid-userfiles-mobilehub-631333021/user_images/fb161ed5-1c51-407a-a60f-28ceec416d9c", 
        "firstName_s": "", 
        "gender_s": "", 
        "shortDescription_s": "not sure", 
        "photoId_s": "fb161ed5-1c51-407a-a60f-28ceec416d9c", 
        "birthday_s": "08/22/2017", 
        "original_username_s": "", 
        "ethnicity_s": "", 
        "userId_s": "us-west-2:ce41b786-0649-4cfb-af0f-b8874c3e4a93", 
        "race_s": "", 
        "facebookId_s": ""
    }, 
    {
        "location_s": "github", 
        "fullName_s": "", 
        "lastName_s": "", 
        "email_s": "", 
        "postsPrivate_n": "0", 
        "username_s": "sciq273", 
        "profilePicUrl_s": "https://s3-us-west-1.amazonaws.com/sciqandroid-userfiles-mobilehub-631333021/user_images/21d44ba4-c8c5-4f40-8fcc-b0d7864304dc", 
        "firstName_s": "", 
        "gender_s": "Male", 
        "shortDescription_s": "testing branch 27.3", 
        "photoId_s": "21d44ba4-c8c5-4f40-8fcc-b0d7864304dc", 
        "birthday_s": "08/27/2017", 
        "original_username_s": "", 
        "ethnicity_s": "Not Hispanic or Latino", 
        "userId_s": "us-west-2:d4dae038-cab0-4dd2-a368-7af9e8d3fad9", 
        "race_s": "Asian", 
        "facebookId_s": ""
    }, 
    {
        "location_s": "141", 
        "fullName_s": "", 
        "lastName_s": "", 
        "email_s": "", 
        "postsPrivate_n": "0", 
        "username_s": "abcuser1", 
        "profilePicUrl_s": "https://s3-us-west-1.amazonaws.com/sciqandroid-userfiles-mobilehub-631333021/user_images/fb161ed5-1c51-407a-a60f-28ceec416d9c", 
        "firstName_s": "", 
        "gender_s": "", 
        "shortDescription_s": "and one two three four 5678", 
        "photoId_s": "fb161ed5-1c51-407a-a60f-28ceec416d9c", 
        "birthday_s": "08/22/2017", 
        "original_username_s": "", 
        "ethnicity_s": "", 
        "userId_s": "us-west-2:da465eb2-5ad1-4831-bc8e-d458420ea5c8", 
        "race_s": "", 
        "facebookId_s": ""
    }, 
    {
        "location_s": "san diego", 
        "fullName_s": "nick phan", 
        "lastName_s": "phan", 
        "email_s": "ngphan@ucsd.edu", 
        "postsPrivate_n": "0", 
        "username_s": "nickphan3", 
        "profilePicUrl_s": "https://s3-us-west-1.amazonaws.com/sciqandroid-userfiles-mobilehub-631333021/user_images/eb51eb00-deac-4e6a-8023-9e7f26e681e3", 
        "firstName_s": "nick", 
        "gender_s": "Male", 
        "shortDescription_s": "asdf", 
        "photoId_s": "eb51eb00-deac-4e6a-8023-9e7f26e681e3", 
        "birthday_s": "10/18/2017", 
        "original_username_s": "nickphan3", 
        "ethnicity_s": "Not Hispanic or Latino", 
        "userId_s": "us-west-2:dba06edf-8313-48d8-934f-102213cfc753", 
        "race_s": "Asian", 
        "facebookId_s": ""
    }, 
    {
        "location_s": "San Diego", 
        "fullName_s": "", 
        "lastName_s": "keng", 
        "email_s": "ckeng@ucsd.edu", 
        "postsPrivate_n": "0", 
        "username_s": "alexiak", 
        "profilePicUrl_s": "https://s3-us-west-1.amazonaws.com/sciqandroid-userfiles-mobilehub-631333021/user_images/36d5189e-684d-4dba-8eef-a695ea69e573", 
        "firstName_s": "alexia", 
        "gender_s": "Female", 
        "shortDescription_s": "Hello", 
        "photoId_s": "36d5189e-684d-4dba-8eef-a695ea69e573", 
        "birthday_s": "01/02/1997", 
        "original_username_s": "alexiak", 
        "ethnicity_s": "Not Hispanic or Latino", 
        "userId_s": "us-west-2:e11b90cf-e0c8-45ad-a524-2ac75e3c3938", 
        "race_s": "Asian", 
        "facebookId_s": ""
    }, 
    {
        "location_s": "San Diego, CA", 
        "fullName_s": "", 
        "lastName_s": "wang", 
        "email_s": "chi1029@gmail.com", 
        "postsPrivate_n": "0", 
        "username_s": "Irene", 
        "profilePicUrl_s": "https://s3-us-west-1.amazonaws.com/sciqandroid-userfiles-mobilehub-631333021/user_images/7e4511e8-eabb-45a5-b2ca-673fb87986b1", 
        "firstName_s": "irene ", 
        "gender_s": "Female", 
        "shortDescription_s": "skin allergy cleared!!!", 
        "photoId_s": "7e4511e8-eabb-45a5-b2ca-673fb87986b1", 
        "birthday_s": "09/19/1986", 
        "original_username_s": "Irene", 
        "ethnicity_s": "Not Hispanic or Latino", 
        "userId_s": "us-west-2:e1586c44-b5b8-4872-aed4-c0da0cf13113", 
        "race_s": "Asian", 
        "facebookId_s": ""
    }, 
    {
        "location_s": "9675 Genesee Ave", 
        "fullName_s": "", 
        "lastName_s": "yu", 
        "email_s": "jiy236@ucsd.edu", 
        "postsPrivate_n": "0", 
        "username_s": "yujingwen199756", 
        "profilePicUrl_s": "https://s3-us-west-1.amazonaws.com/sciqandroid-userfiles-mobilehub-631333021/user_images/0afe96ed-1a68-4cee-adae-b3493af21143", 
        "firstName_s": "jingwen", 
        "gender_s": "Female", 
        "shortDescription_s": "I like play basketball!!!", 
        "photoId_s": "0afe96ed-1a68-4cee-adae-b3493af21143", 
        "birthday_s": "05/06/1997", 
        "original_username_s": "yujingwen199756", 
        "ethnicity_s": "Not Hispanic or Latino", 
        "userId_s": "us-west-2:e4e58797-53ab-467b-9e14-34ff2faed084", 
        "race_s": "Asian", 
        "facebookId_s": ""
    }, 
    {
        "location_s": "san diego", 
        "fullName_s": "", 
        "lastName_s": "wang", 
        "email_s": "shw302@ucsd.edu", 
        "postsPrivate_n": "0", 
        "username_s": "crystal", 
        "profilePicUrl_s": "https://s3-us-west-1.amazonaws.com/sciqandroid-userfiles-mobilehub-631333021/user_images/91b66029-ba34-4f9b-a4e0-8109a2cbb66d", 
        "firstName_s": "crystal", 
        "gender_s": "Female", 
        "shortDescription_s": "hhhhh", 
        "photoId_s": "91b66029-ba34-4f9b-a4e0-8109a2cbb66d", 
        "birthday_s": "05/15/2001", 
        "original_username_s": "crystal", 
        "ethnicity_s": "Not Hispanic or Latino", 
        "userId_s": "us-west-2:e76ad08e-f3d0-468a-8c3e-cacd1ca0cddd", 
        "race_s": "Asian", 
        "facebookId_s": ""
    }, 
    {
        "location_s": "9675 Genesee Ave", 
        "fullName_s": "", 
        "lastName_s": "yu", 
        "email_s": "jiy236@eng.ucsd.edu", 
        "postsPrivate_n": "0", 
        "username_s": "yujingwen", 
        "profilePicUrl_s": "https://s3-us-west-1.amazonaws.com/sciqandroid-userfiles-mobilehub-631333021/user_images/a60d50e5-6b2c-433c-b6e4-50a3f968689c", 
        "firstName_s": "jingwen", 
        "gender_s": "Female", 
        "shortDescription_s": "This is Aliec!!!", 
        "photoId_s": "a60d50e5-6b2c-433c-b6e4-50a3f968689c", 
        "birthday_s": "05/06/1997", 
        "original_username_s": "yujingwen", 
        "ethnicity_s": "Not Hispanic or Latino", 
        "userId_s": "us-west-2:e7ae0453-82d9-478a-8c56-0f9b8ecc205d", 
        "race_s": "Asian", 
        "facebookId_s": ""
    }, 
    {
        "location_s": "abc", 
        "fullName_s": "", 
        "lastName_s": "", 
        "email_s": "", 
        "postsPrivate_n": "", 
        "username_s": "testuser23", 
        "profilePicUrl_s": "https://s3-us-west-1.amazonaws.com/sciqandroid-userfiles-mobilehub-631333021/user_images/testuser23", 
        "firstName_s": "", 
        "gender_s": "", 
        "shortDescription_s": "testing", 
        "photoId_s": "", 
        "birthday_s": "08/22/2017", 
        "original_username_s": "", 
        "ethnicity_s": "", 
        "userId_s": "us-west-2:e9c56c1e-0193-4e30-bf65-a77199129b76", 
        "race_s": "", 
        "facebookId_s": ""
    }, 
    {
        "location_s": "hi", 
        "fullName_s": "", 
        "lastName_s": "", 
        "email_s": "", 
        "postsPrivate_n": "0", 
        "username_s": "person", 
        "profilePicUrl_s": "https://s3-us-west-1.amazonaws.com/sciqandroid-userfiles-mobilehub-631333021/user_images/6c1ffe8f-4c4a-4598-bbd2-b566095ec472", 
        "firstName_s": "", 
        "gender_s": "Male", 
        "shortDescription_s": "hi", 
        "photoId_s": "6c1ffe8f-4c4a-4598-bbd2-b566095ec472", 
        "birthday_s": "08/28/2017", 
        "original_username_s": "", 
        "ethnicity_s": "Not Hispanic or Latino", 
        "userId_s": "us-west-2:eb73c05b-d405-47be-a5eb-80675823df11", 
        "race_s": "Black or African American", 
        "facebookId_s": ""
    }, 
    {
        "location_s": "gdfgdfgf", 
        "fullName_s": "", 
        "lastName_s": "", 
        "email_s": "", 
        "postsPrivate_n": "", 
        "username_s": "kevin12", 
        "profilePicUrl_s": "https://s3-us-west-1.amazonaws.com/sciqandroid-userfiles-mobilehub-631333021/user_images/kevin12", 
        "firstName_s": "", 
        "gender_s": "", 
        "shortDescription_s": "hgfdgdfgdfgdf", 
        "photoId_s": "", 
        "birthday_s": "08/13/2017", 
        "original_username_s": "", 
        "ethnicity_s": "", 
        "userId_s": "us-west-2:f7294aa3-c3be-4ff5-8ead-ce311f3ca4ff", 
        "race_s": "", 
        "facebookId_s": ""
    }, 
    {
        "location_s": "America", 
        "fullName_s": "", 
        "lastName_s": "", 
        "email_s": "cfbn95j@gmail.com", 
        "postsPrivate_n": "0", 
        "username_s": "cfbn95", 
        "profilePicUrl_s": "https://s3-us-west-1.amazonaws.com/sciqandroid-userfiles-mobilehub-631333021/user_images/0920ef9e-7975-4716-a044-8fd2a3d1ce38", 
        "firstName_s": "", 
        "gender_s": "Male", 
        "shortDescription_s": "Testing all stuff", 
        "photoId_s": "0920ef9e-7975-4716-a044-8fd2a3d1ce38", 
        "birthday_s": "10/26/2017", 
        "original_username_s": "cfbn95", 
        "ethnicity_s": "Not Hispanic or Latino", 
        "userId_s": "us-west-2:f9438410-06c4-405c-b928-67eef1fa6d82", 
        "race_s": "Asian", 
        "facebookId_s": ""
    }, 
    {
        "location_s": "a", 
        "fullName_s": "", 
        "lastName_s": "", 
        "email_s": "", 
        "postsPrivate_n": "0", 
        "username_s": "a8", 
        "profilePicUrl_s": "https://s3-us-west-1.amazonaws.com/sciqandroid-userfiles-mobilehub-631333021/user_images/abd2131c-8e49-49f3-a6b5-5907951c612f", 
        "firstName_s": "", 
        "gender_s": "Male", 
        "shortDescription_s": "eight", 
        "photoId_s": "abd2131c-8e49-49f3-a6b5-5907951c612f", 
        "birthday_s": "09/06/2017", 
        "original_username_s": "", 
        "ethnicity_s": "Not Hispanic or Latino", 
        "userId_s": "us-west-2:f94c4a25-4cfe-49cf-b824-915adbac0e22", 
        "race_s": "Asian", 
        "facebookId_s": ""
    }
]